{
	"id": "MQ0fXtarAkSMfvo",
	"json": "{\"id\":\"MQ0fXtarAkSMfvo\",\"url\":\"https://demo-webstore.apify.org/product/lighting-ceiling-kitchen\",\"loadedUrl\":\"https://demo-webstore.apify.org/product/lighting-ceiling-kitchen\",\"uniqueKey\":\"https://demo-webstore.apify.org/product/lighting-ceiling-kitchen\",\"method\":\"GET\",\"noRetry\":false,\"retryCount\":0,\"errorMessages\":[],\"headers\":{},\"userData\":{},\"handledAt\":\"2022-10-27T07:42:05.771Z\"}",
	"method": "GET",
	"orderNo": null,
	"retryCount": 0,
	"uniqueKey": "https://demo-webstore.apify.org/product/lighting-ceiling-kitchen",
	"url": "https://demo-webstore.apify.org/product/lighting-ceiling-kitchen"
}